efpclient/__init__.py
efpclient/configuration.py
efpclient/efpclient.py
efpclient/errors.py
efpclient/logger.py
efpclient/swagger.py
efpclient/utils.py
efpclient/commands/__init__.py
efpclient/commands/admin.py
efpclient/commands/clusters.py
efpclient/commands/hosts.py
efpclient/commands/jobs.py
efpclient/commands/queues.py
efpclient/commands/services.py
efpclient/commands/spoolers.py
efpclient/commands/token.py
efpclient/resources/__init__.py
efpclient/resources/efpclient.conf
efpclient/swagger_client/__init__.py
efpclient/swagger_client/api_client.py
efpclient/swagger_client/configuration.py
efpclient/swagger_client/rest.py
efpclient/swagger_client/api/__init__.py
efpclient/swagger_client/api/default_api.py
efpclient/swagger_client/models/__init__.py
efpclient/swagger_client/models/action.py
efpclient/swagger_client/models/choice.py
efpclient/swagger_client/models/cluster.py
efpclient/swagger_client/models/grid_resource.py
efpclient/swagger_client/models/grid_status.py
efpclient/swagger_client/models/host.py
efpclient/swagger_client/models/item.py
efpclient/swagger_client/models/job.py
efpclient/swagger_client/models/license.py
efpclient/swagger_client/models/license_owner.py
efpclient/swagger_client/models/license_token.py
efpclient/swagger_client/models/option.py
efpclient/swagger_client/models/queue.py
efpclient/swagger_client/models/reason.py
efpclient/swagger_client/models/rest_error.py
efpclient/swagger_client/models/rest_response.py
efpclient/swagger_client/models/service.py
efpclient/swagger_client/models/service_entry.py
efpclient/swagger_client/models/service_param.py
efpclient/swagger_client/models/service_request.py
efpclient/swagger_client/models/service_submission_response.py
efpclient/swagger_client/models/session.py
efpclient/swagger_client/models/size.py
efpclient/swagger_client/models/spooler.py
efpclient-2025.0.4.dist-info/METADATA
efpclient-2025.0.4.dist-info/WHEEL
efpclient-2025.0.4.dist-info/entry_points.txt
efpclient-2025.0.4.dist-info/licenses/LICENSE
efpclient-2025.0.4.dist-info/RECORD
