Metadata-Version: 2.4
Name: efpclient
Version: 2025.0.4
Summary: Command Line Interface to interact with EF Portal.
Project-URL: Homepage, https://www.ni-sp.com/ef-portal/
Author-email: NI SP Software <info@ni-sp-software.com>
License: Apache-2.0
License-File: LICENSE
Keywords: DCV,EF Portal,EnginFrame,HPC,efportal
Classifier: Development Status :: 5 - Production/Stable
Classifier: Operating System :: OS Independent
Classifier: Programming Language :: Python :: 3.9
Classifier: Programming Language :: Python :: 3.10
Classifier: Programming Language :: Python :: 3.11
Classifier: Programming Language :: Python :: 3.12
Classifier: Programming Language :: Python :: 3.13
Requires-Python: >=3.9
Requires-Dist: click>=8.1.8
Requires-Dist: requests>=2.32.3
Requires-Dist: six>=1.17.0
